stencila/schema/__init__.py
stencila/schema/json.py
stencila/schema/types.py
stencila/schema/util.py
stencila_schema-1.16.1.dist-info/METADATA
stencila_schema-1.16.1.dist-info/WHEEL
stencila_schema-1.16.1.dist-info/top_level.txt
stencila_schema-1.16.1.dist-info/RECORD
