Metadata-Version: 2.1
Name: stencila-schema
Version: 1.16.1
Summary: UNKNOWN
Home-page: https://github.com/stencila/schema
Author: Stencila and contributors
Author-email: hello@stenci.la
License: Apache-2.0
Platform: UNKNOWN
Classifier: License :: OSI Approved :: Apache Software License
Classifier: Programming Language :: Python
Classifier: Programming Language :: Python :: 3
Classifier: Programming Language :: Python :: 3.6
Classifier: Programming Language :: Python :: Implementation :: CPython
Classifier: Programming Language :: Python :: Implementation :: PyPy
Requires-Python: >=3.6.0
